nb_log/__init__.py
nb_log/add_python_executable_dir_to_path_env.py
nb_log/capture_warnings.py
nb_log/direct_logger.py
nb_log/exception_auto_log.py
nb_log/file_write.py
nb_log/formatters.py
nb_log/frequency_control_log.py
nb_log/global_except_hook.py
nb_log/handlers.py
nb_log/handlers0000.py
nb_log/handlers_loguru.py
nb_log/handlers_more.py
nb_log/helpers.py
nb_log/log_manager.py
nb_log/logging_tree_helper.py
nb_log/monkey_print.py
nb_log/monkey_std_filter_words.py
nb_log/monkey_sys_std.py
nb_log/nb_log_config_default.py
nb_log/root_logger.py
nb_log/rotate_file_writter.py
nb_log/set_nb_log_config.py
nb_log/simple_print.py
nb_log/loggers_imp/__init__.py
nb_log/loggers_imp/compatible_logger.py
nb_log-13.9.dist-info/METADATA
nb_log-13.9.dist-info/WHEEL
nb_log-13.9.dist-info/top_level.txt
nb_log-13.9.dist-info/RECORD
