Metadata-Version: 2.1
Name: nb_log
Version: 13.9
Summary: very sharp color display,monkey patch bulitin print  and high-performance multiprocess safe roating file handler,other handlers includeing dintalk ,email,kafka,elastic and so on 
Home-page: https://github.com/ydf0509/nb_log
Author: bfzs
Author-email: ydf0509@sohu.com
Maintainer: ydf
Maintainer-email: ydf0509@sohu.com
License: BSD License
Keywords: logging,logger,multiprocess file handler,color handler,loguru
Platform: all
Classifier: Development Status :: 4 - Beta
Classifier: Operating System :: OS Independent
Classifier: Intended Audience :: Developers
Classifier: License :: OSI Approved :: BSD License
Classifier: Programming Language :: Python
Classifier: Programming Language :: Python :: Implementation
Classifier: Programming Language :: Python :: 3
Classifier: Topic :: Software Development :: Libraries
Requires-Dist: tomorrow3==1.1.0
Requires-Dist: concurrent-log-handler==0.9.23
Requires-Dist: requests
Requires-Dist: python-json-logger==0.1.10
Requires-Dist: nb_filelock
Requires-Dist: service-identity
Requires-Dist: deprecated==1.2.14
Requires-Dist: chained_mode_time_tool
Requires-Dist: nb_libs
Requires-Dist: logging_tree
Provides-Extra: all
Requires-Dist: pymongo==4.3.3; extra == "all"
Requires-Dist: elasticsearch; extra == "all"
Requires-Dist: kafka-python==2.0.2; extra == "all"
Requires-Dist: loguru; extra == "all"
